elasticsearch_xpack/__init__.py
elasticsearch_xpack/deprecation.py
elasticsearch_xpack/graph.py
elasticsearch_xpack/license.py
elasticsearch_xpack/migration.py
elasticsearch_xpack/ml.py
elasticsearch_xpack/monitoring.py
elasticsearch_xpack/security.py
elasticsearch_xpack/watcher.py
elasticsearch_xpack-6.0.0.dist-info/DESCRIPTION.rst
elasticsearch_xpack-6.0.0.dist-info/METADATA
elasticsearch_xpack-6.0.0.dist-info/RECORD
elasticsearch_xpack-6.0.0.dist-info/WHEEL
elasticsearch_xpack-6.0.0.dist-info/metadata.json
elasticsearch_xpack-6.0.0.dist-info/top_level.txt
